create_tao_masternode/__init__.py
create_tao_masternode/envs.py
create_tao_masternode/main.py
create_tao_masternode/templates/__init__.py
create_tao_masternode/templates/compose.py
create_tao_masternode/templates/env.py
create_tao_masternode-1.2.6.dist-info/entry_points.txt
create_tao_masternode-1.2.6.dist-info/WHEEL
create_tao_masternode-1.2.6.dist-info/METADATA
create_tao_masternode-1.2.6.dist-info/RECORD
